[
    {
        "key": "dbln",
        "value": "%7B%22100080899898916%22%3A%22Ha8M59wa%22%7D",
        "domain": "facebook.com",
        "path": "/login/device-based/",
        "hostOnly": false,
        "creation": "2024-08-30T03:43:55.826Z",
        "lastAccessed": "2024-08-30T03:43:55.827Z"
    },
    {
        "key": "datr",
        "value": "4yPLZpbp57NMPsCttvm2jxLS",
        "domain": "facebook.com",
        "path": "/",
        "hostOnly": false,
        "creation": "2024-08-30T03:43:55.827Z",
        "lastAccessed": "2024-08-30T03:43:55.827Z"
    },
    {
        "key": "sb",
        "value": "4yPLZgoN94aC-K3XCwwXhb6G",
        "domain": "facebook.com",
        "path": "/",
        "hostOnly": false,
        "creation": "2024-08-30T03:43:55.827Z",
        "lastAccessed": "2024-08-30T03:43:55.827Z"
    },
    {
        "key": "locale",
        "value": "en_GB",
        "domain": "facebook.com",
        "path": "/",
        "hostOnly": false,
        "creation": "2024-08-30T03:43:55.827Z",
        "lastAccessed": "2024-08-30T03:43:55.827Z"
    },
    {
        "key": "vpd",
        "value": "v1%3B746x393x2.75",
        "domain": "facebook.com",
        "path": "/",
        "hostOnly": false,
        "creation": "2024-08-30T03:43:55.827Z",
        "lastAccessed": "2024-08-30T03:43:55.827Z"
    },
    {
        "key": "ps_l",
        "value": "1",
        "domain": "facebook.com",
        "path": "/",
        "hostOnly": false,
        "creation": "2024-08-30T03:43:55.827Z",
        "lastAccessed": "2024-08-30T03:43:55.827Z"
    },
    {
        "key": "ps_n",
        "value": "1",
        "domain": "facebook.com",
        "path": "/",
        "hostOnly": false,
        "creation": "2024-08-30T03:43:55.827Z",
        "lastAccessed": "2024-08-30T03:43:55.827Z"
    },
    {
        "key": "m_pixel_ratio",
        "value": "2.75",
        "domain": "facebook.com",
        "path": "/",
        "hostOnly": false,
        "creation": "2024-08-30T03:43:55.827Z",
        "lastAccessed": "2024-08-30T03:43:55.827Z"
    },
    {
        "key": "wd",
        "value": "393x746",
        "domain": "facebook.com",
        "path": "/",
        "hostOnly": false,
        "creation": "2024-08-30T03:43:55.827Z",
        "lastAccessed": "2024-08-30T03:43:55.827Z"
    },
    {
        "key": "c_user",
        "value": "100080899898916",
        "domain": "facebook.com",
        "path": "/",
        "hostOnly": false,
        "creation": "2024-08-30T03:43:55.827Z",
        "lastAccessed": "2024-08-30T03:43:55.827Z"
    },
    {
        "key": "fr",
        "value": "0vK8JjdbgVZoDe0NS.AWVvSHY7sGXYkimfl6iVYUd2T9I.Bmyzd7..AAA.0.0.Bm0T-1.AWXYxaHbITM",
        "domain": "facebook.com",
        "path": "/",
        "hostOnly": false,
        "creation": "2024-08-30T03:43:55.827Z",
        "lastAccessed": "2024-08-30T03:43:55.827Z"
    },
    {
        "key": "xs",
        "value": "27%3AwPIgmncU_ooyJg%3A2%3A1724989365%3A-1%3A5100",
        "domain": "facebook.com",
        "path": "/",
        "hostOnly": false,
        "creation": "2024-08-30T03:43:55.827Z",
        "lastAccessed": "2024-08-30T03:43:55.827Z"
    },
    {
        "key": "fbl_st",
        "value": "100724763%3BT%3A28749822",
        "domain": "facebook.com",
        "path": "/",
        "hostOnly": false,
        "creation": "2024-08-30T03:43:55.827Z",
        "lastAccessed": "2024-08-30T03:43:55.827Z"
    },
    {
        "key": "wl_cbv",
        "value": "v2%3Bclient_version%3A2605%3Btimestamp%3A1724989368",
        "domain": "facebook.com",
        "path": "/",
        "hostOnly": false,
        "creation": "2024-08-30T03:43:55.827Z",
        "lastAccessed": "2024-08-30T03:43:55.827Z"
    }
]